[
  {
    "title": "LET Lab receives multi-year grant for human-AI collaboration research",
    "date": "2025-04-10",
    "description": "Our team was awarded a new grant to explore trustworthy AI for healthcare decision support systems."
  },
  {
    "title": "New publication accepted at ACM CHI",
    "date": "2025-02-28",
    "description": "Congratulations to the Interactive Systems group for their paper on explainable user interfaces."
  },
  {
    "title": "Welcome our 2025 cohort of graduate researchers",
    "date": "2025-01-15",
    "description": "We are excited to welcome six new graduate students joining the lab this semester."
  }
]
